miPubSub/__init__.py
miPubSub/rabbit.py
miPubSub-0.1.dev1.dist-info/DESCRIPTION.rst
miPubSub-0.1.dev1.dist-info/METADATA
miPubSub-0.1.dev1.dist-info/RECORD
miPubSub-0.1.dev1.dist-info/WHEEL
miPubSub-0.1.dev1.dist-info/metadata.json
miPubSub-0.1.dev1.dist-info/top_level.txt
