Metadata-Version: 2.0
Name: miPubSub
Version: 0.1.dev1
Summary: Publish/Subscribe pattern build with RabbitMQ and Protocol Buffers
Home-page: https://github.com/azylinski/miPubSub
Author: https://twitter.com/ArturZylinski
Author-email: UNKNOWN
License: UNKNOWN
Keywords: publish-subscribe rabbitmq protobuf docker async
Platform: UNKNOWN
Classifier: Development Status :: 1 - Planning
Classifier: Intended Audience :: Developers
Classifier: Topic :: Software Development :: Build Tools
Classifier: License :: OSI Approved :: MIT License
Classifier: Natural Language :: English
Classifier: Operating System :: OS Independent
Classifier: Programming Language :: Python :: 3
Classifier: Programming Language :: Python :: 3.4
Classifier: Programming Language :: Python :: 3.5
Classifier: Programming Language :: Python :: 3.6
Classifier: Programming Language :: Python :: Implementation :: PyPy
Classifier: Topic :: Communications
Classifier: Topic :: Internet
Classifier: Topic :: Software Development :: Libraries
Classifier: Topic :: Software Development :: Libraries :: Python Modules
Classifier: Topic :: System :: Networking
Classifier: Topic :: System :: Software Distribution
Classifier: Topic :: Utilities
Requires-Dist: pika (>=0.11.2)
Requires-Dist: protobuf (>=3.5.1)
